[
    {
        "name": "인성기본형",
        "countOfQs": "32",
        "uid": "10002",
        "quids": "4,5,6,7,8,9,10,11,12,13,14,15,16,17,18,19,20,21,22,23,24,25,26,27,28,29,30,31,32,33,34,35",
        "deleted": "1",
        "updatedDate": "1440401995000"
    },
    {
        "name": "인성고민형",
        "countOfQs": "11",
        "uid": "10003",
        "quids": "36,37,38,39,40,41,42,43,44,45,46",
        "deleted": "1",
        "updatedDate": "1440401995000"
    },
    {
        "name": "직종(사무)",
        "countOfQs": "4",
        "uid": "10004",
        "quids": "47,48,49,50",
        "deleted": "1",
        "updatedDate": "1440401995000"
    },
    {
        "name": "직종(마케팅)",
        "countOfQs": "4",
        "uid": "10005",
        "quids": "51,52,53,54",
        "deleted": "1",
        "updatedDate": "1440401995000"
    },
    {
        "name": "직종(금융)",
        "countOfQs": "4",
        "uid": "10006",
        "quids": "55,56,57,58",
        "deleted": "1",
        "updatedDate": "1440401995000"
    },
    {
        "name": "직종(서비스)",
        "countOfQs": "4",
        "uid": "10007",
        "quids": "59,60,61,62",
        "deleted": "1",
        "updatedDate": "1440401995000"
    },
    {
        "name": "직종(IT)",
        "countOfQs": "5",
        "uid": "10008",
        "quids": "63,64,65,66,67",
        "deleted": "1",
        "updatedDate": "1440401995000"
    },
    {
        "name": "직종(컨설팅)",
        "countOfQs": "3",
        "uid": "10009",
        "quids": "68,69,70",
        "deleted": "1",
        "updatedDate": "1440401995000"
    },
    {
        "name": "직종(전기)",
        "countOfQs": "2",
        "uid": "10010",
        "quids": "71,72",
        "deleted": "1",
        "updatedDate": "1440401995000"
    },
    {
        "name": "인성기본(Eng)",
        "countOfQs": "3",
        "uid": "10011",
        "quids": "73,74,75",
        "deleted": "1",
        "updatedDate": "1440401995000"
    },
    {
        "name": "필수질문TOP5",
        "countOfQs": "5",
        "uid": "10012",
        "quids": "76,77,78,79,80",
        "deleted": "0",
        "updatedDate": "1441279783968"
    },
    {
        "name": "필수영어질문TOP5",
        "countOfQs": "5",
        "uid": "10013",
        "quids": "81,82,83,84,85",
        "deleted": "0",
        "updatedDate": "1441279783968"
    },
    {
        "name": "학교생활",
        "countOfQs": "8",
        "uid": "10014",
        "quids": "86,87,88,89,90,91,92,93",
        "deleted": "1",
        "updatedDate": "1441279783968"
    },
    {
        "name": "지원동기및포부",
        "countOfQs": "9",
        "uid": "10015",
        "quids": "94,95,96,97,98,99,100,101,102",
        "deleted": "1",
        "updatedDate": "1441279783968"
    },
    {
        "name": "장단점",
        "countOfQs": "4",
        "uid": "10016",
        "quids": "103,104,105,106",
        "deleted": "1",
        "updatedDate": "1441279783968"
    },
    {
        "name": "자기소개",
        "countOfQs": "7",
        "uid": "10017",
        "quids": "107,108,109,110,111,112,113",
        "deleted": "0",
        "updatedDate": "1441279783968"
    },
    {
        "name": "논리적사고형",
        "countOfQs": "5",
        "uid": "10018",
        "quids": "114,115,116,117,118",
        "deleted": "1",
        "updatedDate": "1441279783968"
    },
    {
        "name": "고민형",
        "countOfQs": "11",
        "uid": "10019",
        "quids": "119,120,121,122,123,124,125,126,127,128,129",
        "deleted": "1",
        "updatedDate": "1441279783968"
    },
    {
        "name": "개인성향",
        "countOfQs": "17",
        "uid": "10020",
        "quids": "130,131,132,133,134,135,136,137,138,139,140,141,142,143,144,145,146",
        "deleted": "1",
        "updatedDate": "1441279783968"
    },
    {
        "name": "삼성전자",
        "countOfQs": "16",
        "uid": "10021",
        "quids": "147,148,149,150,151,152,153,154,155,156,157,158,159,160,161,162",
        "deleted": "1",
        "updatedDate": "1441279783968"
    }
]
